rftg/__init__.py
rftg/card.py
rftg-0.0.3.dist-info/LICENSE
rftg-0.0.3.dist-info/METADATA
rftg-0.0.3.dist-info/WHEEL
rftg-0.0.3.dist-info/top_level.txt
rftg-0.0.3.dist-info/RECORD
