Metadata-Version: 2.1
Name: rftg
Version: 0.0.3
Summary: AI research project about Race for the Galaxy board game
Home-page: https://github.com/damiencarol/rftg
Author: Damien Carol
Author-email: damien.carol@gmail.com
License: UNKNOWN
Platform: UNKNOWN
Classifier: Development Status :: 4 - Beta
Classifier: Programming Language :: Python
Classifier: Programming Language :: Python :: 3
Classifier: Programming Language :: Python :: 3.6
Classifier: Programming Language :: Python :: 3.7
Classifier: Programming Language :: Python :: 3.8
Classifier: License :: OSI Approved :: GNU General Public License v3 (GPLv3)
Classifier: Operating System :: OS Independent
Requires-Python: >=3.6
